{
  "project_info": {
    "project_number": "389037544240",
    "firebase_url": "https://file-a-case.firebaseio.com",
    "project_id": "file-a-case",
    "storage_bucket": "file-a-case.appspot.com"
  },
  "client": [
    {
      "client_info": {
        "mobilesdk_app_id": "1:389037544240:android:c9073ac989c7b51f",
        "android_client_info": {
          "package_name": "se.cub.fileacase"
        }
      },
      "oauth_client": [
        {
          "client_id": "389037544240-2mlibngj6remhurs18j9n6s9vl0dj29d.apps.googleusercontent.com",
          "client_type": 3
        }
      ],
      "api_key": [
        {
          "current_key": "AIzaSyD_SQbhfVAkyF3aLLf9noAIblv5IRYTgiY"
        }
      ],
      "services": {
        "analytics_service": {
          "status": 1
        },
        "appinvite_service": {
          "status": 1,
          "other_platform_oauth_client": []
        },
        "ads_service": {
          "status": 2
        }
      }
    }
  ],
  "configuration_version": "1"
}